2350_proj2_snider_will/source/params.vh
`ifdef sim
    parameter mydiv = 10;
    parameter mydiv_1 = 4;
`else
    parameter mydiv = 2_500_000;
    parameter mydiv_1 = 1_000_000;
`endif

2350_proj1_snider_will/Source/sevenseg.v
module sevenseg(input [3:0] bits,
                output reg [7:0] out
                );
                
    always @ (*)
        case (bits[3:0])    //7654_3210
            4'b0000: out = 8'b1100_0000;    // 0
            4'b0001: out = 8'b1111_1001;    // 1
            4'b0010: out = 8'b1010_0100;    // 2
            4'b0011: out = 8'b1011_0000;    // 3
            4'b0100: out = 8'b1001_1001;    // 4
            4'b0101: out = 8'b1001_0010;    // 5
            4'b0110: out = 8'b1000_0010;    // 6
            4'b0111: out = 8'b1111_1000;    // 7
            4'b1000: out = 8'b1000_0000;    // 8
            4'b1001: out = 8'b1001_1000;    // 9
            4'b1010: out = 8'b1000_1000;    // A
            4'b1011: out = 8'b1000_0011;    // B
            4'b1100: out = 8'b1100_0110;    // C
            4'b1101: out = 8'b1010_0001;    // D
            4'b1110: out = 8'b1000_0110;    // E
            4'b1111: out = 8'b1000_1110;    // F

            default: out = 8'b1111_1111;
        endcase

endmodule

2350_proj2_snider_will/source/daycounter.v
module daycounter(input clock, input wire reset_n, output [7:0]HEX0, output [7:0]HEX1, output reg [7:0] BCD_value);
    `include "params.vh"
    
    //wire [6:0] binary_value = 0;
    wire [7:0] hex0_t, hex1_t;
    reg [3:0] BCD_t = 0;
    
    always @ (posedge clock, negedge reset_n)
    begin
        if(~reset_n)
            BCD_value <= 1;
        else if (BCD_value[3:0] == 4'b1001 && BCD_value[7:4]==4'b1001)
            BCD_value <= 1;
        else if (BCD_value[3:0]==4'b1001)
        begin
            BCD_value[3:0] <= 0;
            BCD_value[7:4] <= BCD_value[7:4]+1;
        end
        else 
            BCD_value[3:0] <= BCD_value[3:0]+1;
    end
    always @(posedge clock)
    begin
        if (BCD_value[7:4] == 0)
        BCD_t <= 4'b1111;
        else
        BCD_t <= BCD_value[7:4];
    end

    //binary_value = (BCD_value[7:4] * 10) + ({3'b0, BCD_value[3:0]});
    sevenseg U1 (.bits(BCD_value[3:0]), .out(hex0_t));
    sevenseg U2 (.bits(BCD_t), .out(hex1_t));
    assign HEX0 = hex0_t;
    assign HEX1 = hex1_t;
endmodule

2350_proj2_snider_will/source/clock_divider.v
module clock_divider (input clock_in, reset_n, output reg clock_out);
    reg [22:0] clock_divider;
    parameter divide_by = 0;

    always @ (posedge clock_in, negedge reset_n)
        begin
            if(~reset_n)    // reset (active low)
                begin
                    clock_out <= 0;
                    clock_divider <= 0;
                end
            else    // divide clock
                begin
                    if(clock_divider != divide_by - 1)
                        clock_divider <= clock_divider + 1'b1;  // count up to divide_by-1
                    else
                        begin
                            clock_out <= ~clock_out;    // flip clock every time we count to divide_by-1 
                            clock_divider <= 0;         // reset counter back to 0
                        end
                end
        end
        
endmodule

2350_proj2_snider_will/source/top.v
module top(input wire ADC_CLK_10, 
    input [9:0] SW, 
    input [1:0] KEY, 
    output [7:0] HEX0, HEX1, HEX2, HEX4, HEX5,
    output [9:0] LEDR,
    output [6:0] binary_value,
    output reg [7:0] day,
    output reg [3:0] month);
    `include "params.vh"

    wire fiveHzClock, twoHzClock;   // wires to carry clock pulses
    reg dayClock = 0;   // reg to store selected clock
    wire [7:0] BCD_value;

    clock_divider #(mydiv)      U0 (.clock_in(ADC_CLK_10), .reset_n(KEY[0]), .clock_out(twoHzClock));   // divide 10MHz clock to 2Hz
    clock_divider #(mydiv_1)  U1 (.clock_in(ADC_CLK_10), .reset_n(KEY[0]), .clock_out(fiveHzClock));  // divide 10MHz clock to 5Hz

    always @ (*)
    	dayClock = (~KEY[1]) ? fiveHzClock : twoHzClock;    // multiplexor to select clock based on KEY[1] buttonpress

    wire[7:0] hex0_t, hex1_t, hex2_t, hex4_t, hex5_t;   // wires to hold information passed to hex displays

    daycounter U2 (.clock(dayClock), .reset_n(KEY[0]), .HEX0(hex4_t), .HEX1(hex5_t), .BCD_value(BCD_value));   // instantiate daycounter with the selected 2Hz/5Hz clock

    reg l0 = 1'b0;
    reg l1 = 1'b0;  // reg to store the state the light should be in
    always @ (posedge dayClock)
        l0 <= ~l0;   // flip the light every positive edge of the clock
    always @ (negedge dayClock)
        l1 <= ~l1;
    assign LEDR[0] = l0 ^ l1;
    assign HEX4 = hex4_t;
    assign HEX5 = hex5_t;
          
    reg isLeapYear = 1'b0;
    always @ (SW)
        isLeapYear = SW[9] ? 1'b1 : 1'b0;
		  
    reg [3:0] ones;
    reg [3:0] tens;
    
    assign binary_value = (BCD_value[7:4] * 10) + ({3'b0, BCD_value[3:0]});

    always @ (*)
    begin
		   if(~KEY[0])
				month = 4'b0001;
				
        if(binary_value <= 31) // january
            month = 4'b0001;
        else if(31 < binary_value && binary_value <= 59+isLeapYear) //feb
            month = 4'b0010;
        else if (59+isLeapYear < binary_value && binary_value <= isLeapYear+90) // march
            month = 4'b0011;
        else // april
            month = 4'b0100;
    end
	 
    always @(*)
    begin
			if(~KEY[0])
				day = 5'b0_0001;
				
        if (month == 4'b0001)
            day = binary_value;
        else if (month == 4'b0010)
            day = binary_value-31;
        else if (month == 4'b0011)
            day = binary_value - isLeapYear - 59;
        else
            day = binary_value - isLeapYear - 90;
    end
	 
    always @(*)
    begin
			if(~KEY[0])
			begin
				ones = 4'b0001;
            tens = 4'b0000;
			end
			
        if (day < 10)
        begin
            tens <= 4'b1111;
            ones <= day;
        end
        if (day >= 10 && day < 20)
        begin
            tens <= 4'b0001;
            ones <= day -10;
        end
        if (day >= 20 && day <30)
        begin
            tens <= 4'b0010;
            ones <= day -20;
        end
        if (day >= 30)
        begin
            tens <= 4'b0011;
            ones <= day -30;
        end
    end
	 
    sevenseg U3 (.bits(month), .out(hex2_t));
    sevenseg U5 (.bits(tens), .out(hex1_t));
    sevenseg U6 (.bits(ones), .out(hex0_t));

    assign HEX0 = hex0_t;
    assign HEX1 = hex1_t;
    assign HEX2 = hex2_t;
    
endmodule

2350_proj2_snider_will/source/tb.v
`timescale 1 ns / 100 ps
module tb();

reg clock;
reg [9:0] switches;
reg [1:0] key;
wire[7:0] hex0, hex1, hex2, hex4, hex5;
wire[9:0] leds;
wire [7:0] day;
wire [3:0] month;
wire [6:0] day_cnt;
always #10 clock = ~clock;

top TUD (.ADC_CLK_10(clock), .SW(switches), .KEY(key), .HEX0(hex0), .HEX1(hex1), .HEX2(hex2), .HEX4(hex4), .HEX5(hex5), .LEDR(leds),.day(day),.month(month),.binary_value(day_cnt));

initial
    begin
        $dumpfile("output.vcd");
        $dumpvars;
        clock = 0;
        key = 11;
        switches = 10'b00_0000_0000;
end

initial
begin
    $display("Simulation Starting...");
    #5 key = 10;
    #2 key = 11;
    #10 key = 01;
    #3000 key = 11;

    #35000 switches = 10'b10_0000_0000;

    #22000 $finish;
end

initial
    $monitor($time, " clock = %b \t key = %b \t isleap? = %b, Month/day = %d/%d, count = %d,  LEDR[0] = %b, HEX4 =%b", clock, key, switches[9], month, day, day_cnt, leds[0], hex4);

endmodule

2350_proj2_snider_will/TestbenchOutput/output.vcd
$date
	Fri Nov 06 17:12:09 2020
$end
$version
	Icarus Verilog
$end
$timescale
	100ps
$end
$scope module tb $end
$var wire 4 ! month [3:0] $end
$var wire 10 " leds [9:0] $end
$var wire 8 # hex5 [7:0] $end
$var wire 8 $ hex4 [7:0] $end
$var wire 8 % hex2 [7:0] $end
$var wire 8 & hex1 [7:0] $end
$var wire 8 ' hex0 [7:0] $end
$var wire 7 ( day_cnt [6:0] $end
$var wire 8 ) day [7:0] $end
$var reg 1 * clock $end
$var reg 2 + key [1:0] $end
$var reg 10 , switches [9:0] $end
$scope module TUD $end
$var wire 1 * ADC_CLK_10 $end
$var wire 8 - HEX0 [7:0] $end
$var wire 8 . HEX1 [7:0] $end
$var wire 8 / HEX2 [7:0] $end
$var wire 8 0 HEX4 [7:0] $end
$var wire 8 1 HEX5 [7:0] $end
$var wire 2 2 KEY [1:0] $end
$var wire 10 3 SW [9:0] $end
$var wire 1 4 twoHzClock $end
$var wire 8 5 hex5_t [7:0] $end
$var wire 8 6 hex4_t [7:0] $end
$var wire 8 7 hex2_t [7:0] $end
$var wire 8 8 hex1_t [7:0] $end
$var wire 8 9 hex0_t [7:0] $end
$var wire 1 : fiveHzClock $end
$var wire 7 ; binary_value [6:0] $end
$var wire 10 < LEDR [9:0] $end
$var wire 8 = BCD_value [7:0] $end
$var reg 8 > day [7:0] $end
$var reg 1 ? dayClock $end
$var reg 1 @ isLeapYear $end
$var reg 1 A l0 $end
$var reg 1 B l1 $end
$var reg 4 C month [3:0] $end
$var reg 4 D ones [3:0] $end
$var reg 4 E tens [3:0] $end
$scope module U0 $end
$var wire 1 * clock_in $end
$var wire 1 F reset_n $end
$var reg 23 G clock_divider [22:0] $end
$var reg 1 4 clock_out $end
$upscope $end
$scope module U1 $end
$var wire 1 * clock_in $end
$var wire 1 H reset_n $end
$var reg 23 I clock_divider [22:0] $end
$var reg 1 : clock_out $end
$upscope $end
$scope module U2 $end
$var wire 8 J HEX0 [7:0] $end
$var wire 8 K HEX1 [7:0] $end
$var wire 1 ? clock $end
$var wire 1 L reset_n $end
$var wire 8 M hex1_t [7:0] $end
$var wire 8 N hex0_t [7:0] $end
$var reg 4 O BCD_t [3:0] $end
$var reg 8 P BCD_value [7:0] $end
$scope module U1 $end
$var wire 4 Q bits [3:0] $end
$var reg 8 R out [7:0] $end
$upscope $end
$scope module U2 $end
$var wire 4 S bits [3:0] $end
$var reg 8 T out [7:0] $end
$upscope $end
$upscope $end
$scope module U3 $end
$var wire 4 U bits [3:0] $end
$var reg 8 V out [7:0] $end
$upscope $end
$scope module U5 $end
$var wire 4 W bits [3:0] $end
$var reg 8 X out [7:0] $end
$upscope $end
$scope module U6 $end
$var wire 4 Y bits [3:0] $end
$var reg 8 Z out [7:0] $end
$upscope $end
$upscope $end
$upscope $end
$enddefinitions $end
#0
$dumpvars
bx Z
bx Y
bx X
bx W
b10011001 V
b100 U
b11111111 T
bx S
bx R
bx Q
bx P
bx O
bx N
b11111111 M
1L
b11111111 K
bx J
bx I
1H
bx G
1F
bx E
bx D
b100 C
0B
1A
0@
x?
bx >
bx =
bz1 <
bx ;
x:
bx 9
bx 8
b10011001 7
bx 6
b11111111 5
x4
b0 3
b11 2
b11111111 1
bx 0
b10011001 /
bx .
bx -
b0 ,
b11 +
0*
bx )
bx (
bx '
bx &
b10011001 %
bx $
b11111111 #
bz1 "
b100 !
$end
#50
bz0 "
bz0 <
1B
b11111001 %
b11111001 /
b11111001 7
b11111001 V
b11111001 $
b11111001 0
b11111001 6
b11111001 J
b11111001 N
b11111001 R
0?
b1 Q
b1 (
b1 ;
b0 G
04
b0 I
0:
b1 =
b1 P
b11111111 &
b11111111 .
b11111111 8
b11111111 X
b11111001 '
b11111001 -
b11111001 9
b11111001 Z
b1111 E
b1111 W
b1 D
b1 Y
b1 )
b1 >
b1 !
b1 C
b1 U
0F
0H
0L
b10 +
b10 2
#70
1F
1H
1L
b11 +
b11 2
#100
b1 G
b1 I
1*
#170
b1 +
b1 2
#200
0*
#300
b10 G
b10 I
1*
#400
0*
#500
b11 G
b11 I
1*
#600
0*
#700
b10100100 '
b10100100 -
b10100100 9
b10100100 Z
b10 D
b10 Y
b10100100 $
b10100100 0
b10100100 6
b10100100 J
b10100100 N
b10100100 R
b10 )
b10 >
bz1 "
bz1 <
b10 Q
b10 (
b10 ;
0A
b1111 O
b1111 S
b10 =
b10 P
1?
b100 G
b0 I
1:
1*
#800
0*
#900
b101 G
b1 I
1*
#1000
0*
#1100
b110 G
b10 I
1*
#1200
0*
#1300
b111 G
b11 I
1*
#1400
0*
#1500
bz0 "
bz0 <
0B
0?
b1000 G
b0 I
0:
1*
#1600
0*
#1700
b1001 G
b1 I
1*
#1800
0*
#1900
b0 G
14
b10 I
1*
#2000
0*
#2100
b1 G
b11 I
1*
#2200
0*
#2300
b10110000 '
b10110000 -
b10110000 9
b10110000 Z
b11 D
b11 Y
b10110000 $
b10110000 0
b10110000 6
b10110000 J
b10110000 N
b10110000 R
b11 )
b11 >
bz1 "
bz1 <
b11 Q
b11 (
b11 ;
1A
b11 =
b11 P
1?
b10 G
b0 I
1:
1*
#2400
0*
#2500
b11 G
b1 I
1*
#2600
0*
#2700
b100 G
b10 I
1*
#2800
0*
#2900
b101 G
b11 I
1*
#3000
0*
#3100
bz0 "
bz0 <
1B
0?
b110 G
b0 I
0:
1*
#3200
0*
#3300
b111 G
b1 I
1*
#3400
0*
#3500
b1000 G
b10 I
1*
#3600
0*
#3700
b1001 G
b11 I
1*
#3800
0*
#3900
b10011001 '
b10011001 -
b10011001 9
b10011001 Z
b100 D
b100 Y
b10011001 $
b10011001 0
b10011001 6
b10011001 J
b10011001 N
b10011001 R
b100 )
b100 >
bz1 "
bz1 <
b100 Q
b100 (
b100 ;
0A
b100 =
b100 P
1?
b0 G
04
b0 I
1:
1*
#4000
0*
#4100
b1 G
b1 I
1*
#4200
0*
#4300
b10 G
b10 I
1*
#4400
0*
#4500
b11 G
b11 I
1*
#4600
0*
#4700
bz0 "
bz0 <
0B
0?
b100 G
b0 I
0:
1*
#4800
0*
#4900
b101 G
b1 I
1*
#5000
0*
#5100
b110 G
b10 I
1*
#5200
0*
#5300
b111 G
b11 I
1*
#5400
0*
#5500
b10010010 '
b10010010 -
b10010010 9
b10010010 Z
b101 D
b101 Y
b10010010 $
b10010010 0
b10010010 6
b10010010 J
b10010010 N
b10010010 R
b101 )
b101 >
bz1 "
bz1 <
b101 Q
b101 (
b101 ;
1A
b101 =
b101 P
1?
b1000 G
b0 I
1:
1*
#5600
0*
#5700
b1001 G
b1 I
1*
#5800
0*
#5900
b0 G
14
b10 I
1*
#6000
0*
#6100
b1 G
b11 I
1*
#6200
0*
#6300
bz0 "
bz0 <
1B
0?
b10 G
b0 I
0:
1*
#6400
0*
#6500
b11 G
b1 I
1*
#6600
0*
#6700
b100 G
b10 I
1*
#6800
0*
#6900
b101 G
b11 I
1*
#7000
0*
#7100
b10000010 '
b10000010 -
b10000010 9
b10000010 Z
b110 D
b110 Y
b10000010 $
b10000010 0
b10000010 6
b10000010 J
b10000010 N
b10000010 R
b110 )
b110 >
bz1 "
bz1 <
b110 Q
b110 (
b110 ;
0A
b110 =
b110 P
1?
b110 G
b0 I
1:
1*
#7200
0*
#7300
b111 G
b1 I
1*
#7400
0*
#7500
b1000 G
b10 I
1*
#7600
0*
#7700
b1001 G
b11 I
1*
#7800
0*
#7900
bz0 "
bz0 <
0B
0?
b0 G
04
b0 I
0:
1*
#8000
0*
#8100
b1 G
b1 I
1*
#8200
0*
#8300
b10 G
b10 I
1*
#8400
0*
#8500
b11 G
b11 I
1*
#8600
0*
#8700
b11111000 '
b11111000 -
b11111000 9
b11111000 Z
b111 D
b111 Y
b11111000 $
b11111000 0
b11111000 6
b11111000 J
b11111000 N
b11111000 R
b111 )
b111 >
bz1 "
bz1 <
b111 Q
b111 (
b111 ;
1A
b111 =
b111 P
1?
b100 G
b0 I
1:
1*
#8800
0*
#8900
b101 G
b1 I
1*
#9000
0*
#9100
b110 G
b10 I
1*
#9200
0*
#9300
b111 G
b11 I
1*
#9400
0*
#9500
bz0 "
bz0 <
1B
0?
b1000 G
b0 I
0:
1*
#9600
0*
#9700
b1001 G
b1 I
1*
#9800
0*
#9900
b0 G
14
b10 I
1*
#10000
0*
#10100
b1 G
b11 I
1*
#10200
0*
#10300
b10000000 '
b10000000 -
b10000000 9
b10000000 Z
b1000 D
b1000 Y
b10000000 $
b10000000 0
b10000000 6
b10000000 J
b10000000 N
b10000000 R
b1000 )
b1000 >
bz1 "
bz1 <
b1000 Q
b1000 (
b1000 ;
0A
b1000 =
b1000 P
1?
b10 G
b0 I
1:
1*
#10400
0*
#10500
b11 G
b1 I
1*
#10600
0*
#10700
b100 G
b10 I
1*
#10800
0*
#10900
b101 G
b11 I
1*
#11000
0*
#11100
bz0 "
bz0 <
0B
0?
b110 G
b0 I
0:
1*
#11200
0*
#11300
b111 G
b1 I
1*
#11400
0*
#11500
b1000 G
b10 I
1*
#11600
0*
#11700
b1001 G
b11 I
1*
#11800
0*
#11900
b10011000 '
b10011000 -
b10011000 9
b10011000 Z
b1001 D
b1001 Y
b10011000 $
b10011000 0
b10011000 6
b10011000 J
b10011000 N
b10011000 R
b1001 )
b1001 >
bz1 "
bz1 <
b1001 Q
b1001 (
b1001 ;
1A
b1001 =
b1001 P
1?
b0 G
04
b0 I
1:
1*
#12000
0*
#12100
b1 G
b1 I
1*
#12200
0*
#12300
b10 G
b10 I
1*
#12400
0*
#12500
b11 G
b11 I
1*
#12600
0*
#12700
bz0 "
bz0 <
1B
0?
b100 G
b0 I
0:
1*
#12800
0*
#12900
b101 G
b1 I
1*
#13000
0*
#13100
b110 G
b10 I
1*
#13200
0*
#13300
b111 G
b11 I
1*
#13400
0*
#13500
b11000000 '
b11000000 -
b11000000 9
b11000000 Z
b11111001 &
b11111001 .
b11111001 8
b11111001 X
b0 D
b0 Y
b1 E
b1 W
b11000000 $
b11000000 0
b11000000 6
b11000000 J
b11000000 N
b11000000 R
b1010 )
b1010 >
bz1 "
bz1 <
b0 Q
b1010 (
b1010 ;
0A
b10000 =
b10000 P
1?
b1000 G
b0 I
1:
1*
#13600
0*
#13700
b1001 G
b1 I
1*
#13800
0*
#13900
b0 G
14
b10 I
1*
#14000
0*
#14100
b1 G
b11 I
1*
#14200
0*
#14300
bz0 "
bz0 <
0B
0?
b10 G
b0 I
0:
1*
#14400
0*
#14500
b11 G
b1 I
1*
#14600
0*
#14700
b100 G
b10 I
1*
#14800
0*
#14900
b101 G
b11 I
1*
#15000
0*
#15100
b11111001 '
b11111001 -
b11111001 9
b11111001 Z
b1 D
b1 Y
b11111001 $
b11111001 0
b11111001 6
b11111001 J
b11111001 N
b11111001 R
b1011 )
b1011 >
b11111001 #
b11111001 1
b11111001 5
b11111001 K
b11111001 M
b11111001 T
bz1 "
bz1 <
b1 Q
b1011 (
b1011 ;
b1 O
b1 S
1A
b10001 =
b10001 P
1?
b110 G
b0 I
1:
1*
#15200
0*
#15300
b111 G
b1 I
1*
#15400
0*
#15500
b1000 G
b10 I
1*
#15600
0*
#15700
b1001 G
b11 I
1*
#15800
0*
#15900
bz0 "
bz0 <
1B
0?
b0 G
04
b0 I
0:
1*
#16000
0*
#16100
b1 G
b1 I
1*
#16200
0*
#16300
b10 G
b10 I
1*
#16400
0*
#16500
b11 G
b11 I
1*
#16600
0*
#16700
b10100100 '
b10100100 -
b10100100 9
b10100100 Z
b10 D
b10 Y
b10100100 $
b10100100 0
b10100100 6
b10100100 J
b10100100 N
b10100100 R
b1100 )
b1100 >
bz1 "
bz1 <
b10 Q
b1100 (
b1100 ;
0A
b10010 =
b10010 P
1?
b100 G
b0 I
1:
1*
#16800
0*
#16900
b101 G
b1 I
1*
#17000
0*
#17100
b110 G
b10 I
1*
#17200
0*
#17300
b111 G
b11 I
1*
#17400
0*
#17500
bz0 "
bz0 <
0B
0?
b1000 G
b0 I
0:
1*
#17600
0*
#17700
b1001 G
b1 I
1*
#17800
0*
#17900
b0 G
14
b10 I
1*
#18000
0*
#18100
b1 G
b11 I
1*
#18200
0*
#18300
b10110000 '
b10110000 -
b10110000 9
b10110000 Z
b11 D
b11 Y
b10110000 $
b10110000 0
b10110000 6
b10110000 J
b10110000 N
b10110000 R
b1101 )
b1101 >
bz1 "
bz1 <
b11 Q
b1101 (
b1101 ;
1A
b10011 =
b10011 P
1?
b10 G
b0 I
1:
1*
#18400
0*
#18500
b11 G
b1 I
1*
#18600
0*
#18700
b100 G
b10 I
1*
#18800
0*
#18900
b101 G
b11 I
1*
#19000
0*
#19100
bz0 "
bz0 <
1B
0?
b110 G
b0 I
0:
1*
#19200
0*
#19300
b111 G
b1 I
1*
#19400
0*
#19500
b1000 G
b10 I
1*
#19600
0*
#19700
b1001 G
b11 I
1*
#19800
0*
#19900
b10011001 '
b10011001 -
b10011001 9
b10011001 Z
b100 D
b100 Y
b10011001 $
b10011001 0
b10011001 6
b10011001 J
b10011001 N
b10011001 R
b1110 )
b1110 >
bz1 "
bz1 <
b100 Q
b1110 (
b1110 ;
0A
b10100 =
b10100 P
1?
b0 G
04
b0 I
1:
1*
#20000
0*
#20100
b1 G
b1 I
1*
#20200
0*
#20300
b10 G
b10 I
1*
#20400
0*
#20500
b11 G
b11 I
1*
#20600
0*
#20700
bz0 "
bz0 <
0B
0?
b100 G
b0 I
0:
1*
#20800
0*
#20900
b101 G
b1 I
1*
#21000
0*
#21100
b110 G
b10 I
1*
#21200
0*
#21300
b111 G
b11 I
1*
#21400
0*
#21500
b10010010 '
b10010010 -
b10010010 9
b10010010 Z
b101 D
b101 Y
b10010010 $
b10010010 0
b10010010 6
b10010010 J
b10010010 N
b10010010 R
b1111 )
b1111 >
bz1 "
bz1 <
b101 Q
b1111 (
b1111 ;
1A
b10101 =
b10101 P
1?
b1000 G
b0 I
1:
1*
#21600
0*
#21700
b1001 G
b1 I
1*
#21800
0*
#21900
b0 G
14
b10 I
1*
#22000
0*
#22100
b1 G
b11 I
1*
#22200
0*
#22300
bz0 "
bz0 <
1B
0?
b10 G
b0 I
0:
1*
#22400
0*
#22500
b11 G
b1 I
1*
#22600
0*
#22700
b100 G
b10 I
1*
#22800
0*
#22900
b101 G
b11 I
1*
#23000
0*
#23100
b10000010 '
b10000010 -
b10000010 9
b10000010 Z
b110 D
b110 Y
b10000010 $
b10000010 0
b10000010 6
b10000010 J
b10000010 N
b10000010 R
b10000 )
b10000 >
bz1 "
bz1 <
b110 Q
b10000 (
b10000 ;
0A
b10110 =
b10110 P
1?
b110 G
b0 I
1:
1*
#23200
0*
#23300
b111 G
b1 I
1*
#23400
0*
#23500
b1000 G
b10 I
1*
#23600
0*
#23700
b1001 G
b11 I
1*
#23800
0*
#23900
bz0 "
bz0 <
0B
0?
b0 G
04
b0 I
0:
1*
#24000
0*
#24100
b1 G
b1 I
1*
#24200
0*
#24300
b10 G
b10 I
1*
#24400
0*
#24500
b11 G
b11 I
1*
#24600
0*
#24700
b11111000 '
b11111000 -
b11111000 9
b11111000 Z
b111 D
b111 Y
b11111000 $
b11111000 0
b11111000 6
b11111000 J
b11111000 N
b11111000 R
b10001 )
b10001 >
bz1 "
bz1 <
b111 Q
b10001 (
b10001 ;
1A
b10111 =
b10111 P
1?
b100 G
b0 I
1:
1*
#24800
0*
#24900
b101 G
b1 I
1*
#25000
0*
#25100
b110 G
b10 I
1*
#25200
0*
#25300
b111 G
b11 I
1*
#25400
0*
#25500
bz0 "
bz0 <
1B
0?
b1000 G
b0 I
0:
1*
#25600
0*
#25700
b1001 G
b1 I
1*
#25800
0*
#25900
b0 G
14
b10 I
1*
#26000
0*
#26100
b1 G
b11 I
1*
#26200
0*
#26300
b10000000 '
b10000000 -
b10000000 9
b10000000 Z
b1000 D
b1000 Y
b10000000 $
b10000000 0
b10000000 6
b10000000 J
b10000000 N
b10000000 R
b10010 )
b10010 >
bz1 "
bz1 <
b1000 Q
b10010 (
b10010 ;
0A
b11000 =
b11000 P
1?
b10 G
b0 I
1:
1*
#26400
0*
#26500
b11 G
b1 I
1*
#26600
0*
#26700
b100 G
b10 I
1*
#26800
0*
#26900
b101 G
b11 I
1*
#27000
0*
#27100
bz0 "
bz0 <
0B
0?
b110 G
b0 I
0:
1*
#27200
0*
#27300
b111 G
b1 I
1*
#27400
0*
#27500
b1000 G
b10 I
1*
#27600
0*
#27700
b1001 G
b11 I
1*
#27800
0*
#27900
b10011000 '
b10011000 -
b10011000 9
b10011000 Z
b1001 D
b1001 Y
b10011000 $
b10011000 0
b10011000 6
b10011000 J
b10011000 N
b10011000 R
b10011 )
b10011 >
bz1 "
bz1 <
b1001 Q
b10011 (
b10011 ;
1A
b11001 =
b11001 P
1?
b0 G
04
b0 I
1:
1*
#28000
0*
#28100
b1 G
b1 I
1*
#28200
0*
#28300
b10 G
b10 I
1*
#28400
0*
#28500
b11 G
b11 I
1*
#28600
0*
#28700
bz0 "
bz0 <
1B
0?
b100 G
b0 I
0:
1*
#28800
0*
#28900
b101 G
b1 I
1*
#29000
0*
#29100
b110 G
b10 I
1*
#29200
0*
#29300
b111 G
b11 I
1*
#29400
0*
#29500
b11000000 '
b11000000 -
b11000000 9
b11000000 Z
b10100100 &
b10100100 .
b10100100 8
b10100100 X
b0 D
b0 Y
b10 E
b10 W
b11000000 $
b11000000 0
b11000000 6
b11000000 J
b11000000 N
b11000000 R
b10100 )
b10100 >
bz1 "
bz1 <
b0 Q
b10100 (
b10100 ;
0A
b100000 =
b100000 P
1?
b1000 G
b0 I
1:
1*
#29600
0*
#29700
b1001 G
b1 I
1*
#29800
0*
#29900
b0 G
14
b10 I
1*
#30000
0*
#30100
b1 G
b11 I
1*
#30170
b11 +
b11 2
#30200
0*
#30300
b10 G
b0 I
0:
1*
#30400
0*
#30500
b11 G
b1 I
1*
#30600
0*
#30700
b100 G
b10 I
1*
#30800
0*
#30900
b101 G
b11 I
1*
#31000
0*
#31100
b110 G
b0 I
1:
1*
#31200
0*
#31300
b111 G
b1 I
1*
#31400
0*
#31500
b1000 G
b10 I
1*
#31600
0*
#31700
b1001 G
b11 I
1*
#31800
0*
#31900
bz0 "
bz0 <
0B
0?
b0 G
04
b0 I
0:
1*
#32000
0*
#32100
b1 G
b1 I
1*
#32200
0*
#32300
b10 G
b10 I
1*
#32400
0*
#32500
b11 G
b11 I
1*
#32600
0*
#32700
b100 G
b0 I
1:
1*
#32800
0*
#32900
b101 G
b1 I
1*
#33000
0*
#33100
b110 G
b10 I
1*
#33200
0*
#33300
b111 G
b11 I
1*
#33400
0*
#33500
b1000 G
b0 I
0:
1*
#33600
0*
#33700
b1001 G
b1 I
1*
#33800
0*
#33900
b11111001 '
b11111001 -
b11111001 9
b11111001 Z
b1 D
b1 Y
b11111001 $
b11111001 0
b11111001 6
b11111001 J
b11111001 N
b11111001 R
b10101 )
b10101 >
b10100100 #
b10100100 1
b10100100 5
b10100100 K
b10100100 M
b10100100 T
bz1 "
bz1 <
b1 Q
b10101 (
b10101 ;
b10 O
b10 S
1A
b100001 =
b100001 P
1?
b0 G
14
b10 I
1*
#34000
0*
#34100
b1 G
b11 I
1*
#34200
0*
#34300
b10 G
b0 I
1:
1*
#34400
0*
#34500
b11 G
b1 I
1*
#34600
0*
#34700
b100 G
b10 I
1*
#34800
0*
#34900
b101 G
b11 I
1*
#35000
0*
#35100
b110 G
b0 I
0:
1*
#35200
0*
#35300
b111 G
b1 I
1*
#35400
0*
#35500
b1000 G
b10 I
1*
#35600
0*
#35700
b1001 G
b11 I
1*
#35800
0*
#35900
bz0 "
bz0 <
1B
0?
b0 G
04
b0 I
1:
1*
#36000
0*
#36100
b1 G
b1 I
1*
#36200
0*
#36300
b10 G
b10 I
1*
#36400
0*
#36500
b11 G
b11 I
1*
#36600
0*
#36700
b100 G
b0 I
0:
1*
#36800
0*
#36900
b101 G
b1 I
1*
#37000
0*
#37100
b110 G
b10 I
1*
#37200
0*
#37300
b111 G
b11 I
1*
#37400
0*
#37500
b1000 G
b0 I
1:
1*
#37600
0*
#37700
b1001 G
b1 I
1*
#37800
0*
#37900
b10100100 '
b10100100 -
b10100100 9
b10100100 Z
b10 D
b10 Y
b10100100 $
b10100100 0
b10100100 6
b10100100 J
b10100100 N
b10100100 R
b10110 )
b10110 >
bz1 "
bz1 <
b10 Q
b10110 (
b10110 ;
0A
b100010 =
b100010 P
1?
b0 G
14
b10 I
1*
#38000
0*
#38100
b1 G
b11 I
1*
#38200
0*
#38300
b10 G
b0 I
0:
1*
#38400
0*
#38500
b11 G
b1 I
1*
#38600
0*
#38700
b100 G
b10 I
1*
#38800
0*
#38900
b101 G
b11 I
1*
#39000
0*
#39100
b110 G
b0 I
1:
1*
#39200
0*
#39300
b111 G
b1 I
1*
#39400
0*
#39500
b1000 G
b10 I
1*
#39600
0*
#39700
b1001 G
b11 I
1*
#39800
0*
#39900
bz0 "
bz0 <
0B
0?
b0 G
04
b0 I
0:
1*
#40000
0*
#40100
b1 G
b1 I
1*
#40200
0*
#40300
b10 G
b10 I
1*
#40400
0*
#40500
b11 G
b11 I
1*
#40600
0*
#40700
b100 G
b0 I
1:
1*
#40800
0*
#40900
b101 G
b1 I
1*
#41000
0*
#41100
b110 G
b10 I
1*
#41200
0*
#41300
b111 G
b11 I
1*
#41400
0*
#41500
b1000 G
b0 I
0:
1*
#41600
0*
#41700
b1001 G
b1 I
1*
#41800
0*
#41900
b10110000 '
b10110000 -
b10110000 9
b10110000 Z
b11 D
b11 Y
b10110000 $
b10110000 0
b10110000 6
b10110000 J
b10110000 N
b10110000 R
b10111 )
b10111 >
bz1 "
bz1 <
b11 Q
b10111 (
b10111 ;
1A
b100011 =
b100011 P
1?
b0 G
14
b10 I
1*
#42000
0*
#42100
b1 G
b11 I
1*
#42200
0*
#42300
b10 G
b0 I
1:
1*
#42400
0*
#42500
b11 G
b1 I
1*
#42600
0*
#42700
b100 G
b10 I
1*
#42800
0*
#42900
b101 G
b11 I
1*
#43000
0*
#43100
b110 G
b0 I
0:
1*
#43200
0*
#43300
b111 G
b1 I
1*
#43400
0*
#43500
b1000 G
b10 I
1*
#43600
0*
#43700
b1001 G
b11 I
1*
#43800
0*
#43900
bz0 "
bz0 <
1B
0?
b0 G
04
b0 I
1:
1*
#44000
0*
#44100
b1 G
b1 I
1*
#44200
0*
#44300
b10 G
b10 I
1*
#44400
0*
#44500
b11 G
b11 I
1*
#44600
0*
#44700
b100 G
b0 I
0:
1*
#44800
0*
#44900
b101 G
b1 I
1*
#45000
0*
#45100
b110 G
b10 I
1*
#45200
0*
