2350_proj3_snider_will/Source/states.vh
parameter IDLE = 4'd0;
parameter HAZARD = 4'd1;
parameter TURN_LEFT = 4'd2;
parameter TURN_RIGHT = 4'd3;
parameter BRAKE_TURN_RIGHT = 4'd4;
parameter BRAKE_TURN_LEFT = 4'd5;
parameter BRAKE = 4'd6;

`ifdef sim
    parameter div_2Hz = 4;
    parameter div_4Hz = 2;
`else
    parameter div_2Hz = 2_500_000;
    parameter div_4Hz = 1_250_000;
`endif

2350_proj3_snider_will/Source/sevenseg.v
module sevenseg(input [3:0] bits,
                output reg [7:0] out
                );
                
    always @ (*)
        case (bits[3:0])    //7654_3210
            4'b0000: out = 8'b1100_0000;    // 0
            4'b0001: out = 8'b1111_1001;    // 1
            4'b0010: out = 8'b1010_0100;    // 2
            4'b0011: out = 8'b1011_0000;    // 3
            4'b0100: out = 8'b1001_1001;    // 4
            4'b0101: out = 8'b1001_0010;    // 5
            4'b0110: out = 8'b1000_0010;    // 6
            4'b0111: out = 8'b1111_1000;    // 7
            4'b1000: out = 8'b1000_0000;    // 8
            4'b1001: out = 8'b1001_1000;    // 9
            4'b1010: out = 8'b1000_1000;    // A
            4'b1011: out = 8'b1000_0011;    // B
            4'b1100: out = 8'b1100_0110;    // C
            4'b1101: out = 8'b1010_0001;    // D
            4'b1110: out = 8'b1000_0110;    // E
            4'b1111: out = 8'b1111_1111;    // F

            default: out = 8'b1111_1111;
        endcase

endmodule

2350_proj3_snider_will/Source/OL.v
module OL(clock, CurrentState, LEDR);
`include "states.vh"
input clock;
input [3:0] CurrentState;
output [9:0] LEDR;
reg [9:0] leds = 10'b00_0000_0000;
reg [9:0] turn_led_right = 10'b00_0000_0000;
reg [9:0] turn_led_left = 10'b00_0000_0000;
reg [9:0] hazard = 10'b0;
//break
reg [9:0] brake = 10'b111_0000_111;

reg [2:0] cnt = 0;
always @(posedge clock) 
begin
    cnt <= (cnt == 3'd3)? 0: cnt + 1;
    //turn signals
    if (cnt ==0)
        turn_led_right <= 10'b00_0000_0000;
    if(cnt == 1)
        turn_led_right <= 10'b00_0000_0100;
    if(cnt == 2)
        turn_led_right <= 10'b00_0000_0110;
    if(cnt == 3)
        turn_led_right <= 10'b00_0000_0111;
    if (cnt ==0)
        turn_led_left <= 10'b00_0000_0000;
    if(cnt == 1)
        turn_led_left <= 10'b00_1000_0000;
    if(cnt == 2)
        turn_led_left <= 10'b01_1000_0000;
    if(cnt == 3)
        turn_led_left <= 10'b11_1000_0000;
    //hazards
    if (cnt==3)
        hazard <= ~hazard;
end
always @(*)
begin
    case(CurrentState)
    IDLE:   leds <= 10'd0;
    HAZARD: begin
        leds[9:7] <= hazard[9:7];
        leds[2:0] <= hazard[2:0];
    end 
    TURN_LEFT:  leds <= turn_led_left;
    TURN_RIGHT: leds <= turn_led_right;
    BRAKE:      leds <= brake;
    BRAKE_TURN_RIGHT: begin
        leds[9:7] <= brake;
        leds[2:0] <= turn_led_right[2:0];
    end
    BRAKE_TURN_LEFT: begin
        leds[2:0] <= brake;
        leds[9:7] <= turn_led_left[9:7];       
    end
    endcase
end
assign LEDR = leds;
endmodule

2350_proj3_snider_will/Source/CSL.v
module CSL (clock, reset_n, NextState, CurrentState);
`include "states.vh"
input clock, reset_n;
input [3:0] NextState;
output reg [3:0] CurrentState;

always @ (posedge clock, negedge reset_n)
begin
    if(reset_n == 0)
        CurrentState <= IDLE;
    else
        CurrentState <= NextState;
end

endmodule

2350_proj3_snider_will/Source/NSL.v
module NSL (SW, KEY, NextState);
`include "states.vh"
input KEY;
input [2:0] SW;
output reg [3:0] NextState;
wire [4:0] NS = {KEY, SW[2:0]};

always @ (*)
begin
    case (NS)
        4'b0000:     NextState <= IDLE;
        4'b0001:     NextState <= HAZARD;
        4'b0010:     NextState <= TURN_RIGHT;
        4'b0011:     NextState <= HAZARD;
        4'b0100:     NextState <= BRAKE;
        4'b0101:     NextState <= HAZARD;
        4'b0110:     NextState <= BRAKE_TURN_RIGHT;
        4'b0111:     NextState <= HAZARD;
        4'b1000:     NextState <= IDLE;
        4'b1001:     NextState <= HAZARD;
        4'b1010:     NextState <= TURN_LEFT;
        4'b1011:     NextState <= HAZARD;
        4'b1100:     NextState <= BRAKE;
        4'b1101:     NextState <= HAZARD;
        4'b1110:     NextState <= BRAKE_TURN_LEFT;
        4'b1111:     NextState <= HAZARD;
        default: NextState <= IDLE;
    endcase
end
endmodule

2350_proj2_snider_will/source/clock_divider.v
module clock_divider (input clock_in, reset_n, output reg clock_out);
    reg [22:0] clock_divider;
    parameter divide_by = 0;

    always @ (posedge clock_in, negedge reset_n)
        begin
            if(~reset_n)    // reset (active low)
                begin
                    clock_out <= 0;
                    clock_divider <= 0;
                end
            else    // divide clock
                begin
                    if(clock_divider != divide_by - 1)
                        clock_divider <= clock_divider + 1'b1;  // count up to divide_by-1
                    else
                        begin
                            clock_out <= ~clock_out;    // flip clock every time we count to divide_by-1 
                            clock_divider <= 0;         // reset counter back to 0
                        end
                end
        end
        
endmodule

2350_proj3_snider_will/Source/top.v
module top(input ADC_CLK_10, input [1:0] KEY,input [9:0] SW, output [9:0] LEDR, output [7:0] HEX0);
    `include "states.vh"
    wire [3:0] CurrentState;
    wire [3:0] NextState;
    wire twoHzClock;
    wire fourHzClock;

    clock_divider #(div_2Hz) CLKD2 (.clock_in(ADC_CLK_10), .reset_n(KEY[0]), .clock_out(twoHzClock));
    clock_divider #(div_4Hz) CLKD4 (.clock_in(ADC_CLK_10), .reset_n(KEY[0]), .clock_out(fourHzClock));

    NSL U0 (.KEY(KEY[1]), .SW(SW[2:0]), .NextState(NextState));
    CSL U1 (.clock(twoHzClock), .reset_n(KEY[0]), .NextState(NextState), .CurrentState(CurrentState));
    OL  U2 (.clock(fourHzClock), .CurrentState(CurrentState), .LEDR(LEDR));

    sevenseg U3 (.bits(CurrentState),.out(HEX0));
endmodule

2350_proj3_snider_will/Source/tb.v
`timescale 1 ns / 100 ps
module tb();

reg clock;
reg [9:0] switches;
reg [1:0] key;
wire[7:0] hex0;
wire[9:0] leds;

always #10 clock = ~clock;

top TUD (.ADC_CLK_10(clock), .KEY(key), .SW(switches), .LEDR(leds), .HEX0(hex0));

initial
    begin
        $dumpfile("output.vcd");
        $dumpvars;
        clock = 0;
        key = 11;
        switches = 10'b00_0000_0000;
end

initial
begin
    $display("Simulation Starting...");
    #5 key = 10;
    #2 key = 11;
    #100 switches = 10'b00_0000_0100;
    #700 switches = 10'b00_0000_0010;
    #700 key = 01;
    #700 switches = 10'b00_0000_0001;
    #700 switches = 10'b00_0000_0111;
    #700 switches = 10'b00_0000_0110;
    #700 key = 11;
    #700 $finish;
end

initial
    $monitor($time, " clock = %b \t key = %b switches = %b \t LEDR = %b, HEX0 = %b", clock, key, switches, leds, hex0);

endmodule

2350_proj3_snider_will/TestbenchOutput/output.vcd
$date
	Thu Nov 26 16:57:52 2020
$end
$version
	Icarus Verilog
$end
$timescale
	100ps
$end
$scope module tb $end
$var wire 10 ! leds [9:0] $end
$var wire 8 " hex0 [7:0] $end
$var reg 1 # clock $end
$var reg 2 $ key [1:0] $end
$var reg 10 % switches [9:0] $end
$scope module TUD $end
$var wire 1 # ADC_CLK_10 $end
$var wire 2 & KEY [1:0] $end
$var wire 10 ' SW [9:0] $end
$var wire 1 ( twoHzClock $end
$var wire 1 ) fourHzClock $end
$var wire 4 * NextState [3:0] $end
$var wire 10 + LEDR [9:0] $end
$var wire 8 , HEX0 [7:0] $end
$var wire 4 - CurrentState [3:0] $end
$scope module CLKD2 $end
$var wire 1 # clock_in $end
$var wire 1 . reset_n $end
$var reg 23 / clock_divider [22:0] $end
$var reg 1 ( clock_out $end
$upscope $end
$scope module CLKD4 $end
$var wire 1 # clock_in $end
$var wire 1 0 reset_n $end
$var reg 23 1 clock_divider [22:0] $end
$var reg 1 ) clock_out $end
$upscope $end
$scope module U0 $end
$var wire 1 2 KEY $end
$var wire 3 3 SW [2:0] $end
$var wire 5 4 NS [4:0] $end
$var reg 4 5 NextState [3:0] $end
$upscope $end
$scope module U1 $end
$var wire 4 6 NextState [3:0] $end
$var wire 1 ( clock $end
$var wire 1 7 reset_n $end
$var reg 4 8 CurrentState [3:0] $end
$upscope $end
$scope module U2 $end
$var wire 4 9 CurrentState [3:0] $end
$var wire 10 : LEDR [9:0] $end
$var wire 1 ) clock $end
$var reg 10 ; brake [9:0] $end
$var reg 3 < cnt [2:0] $end
$var reg 10 = hazard [9:0] $end
$var reg 10 > leds [9:0] $end
$var reg 10 ? turn_led_left [9:0] $end
$var reg 10 @ turn_led_right [9:0] $end
$upscope $end
$scope module U3 $end
$var wire 4 A bits [3:0] $end
$var reg 8 B out [7:0] $end
$upscope $end
$upscope $end
$upscope $end
$enddefinitions $end
#0
$dumpvars
bx B
bx A
b0 @
b0 ?
b0 >
b0 =
b0 <
b1110000111 ;
b0 :
bx 9
bx 8
17
b0 6
b0 5
b1000 4
b0 3
12
bx 1
10
bx /
1.
bx -
bx ,
b0 +
b0 *
x)
x(
b0 '
b11 &
b0 %
b11 $
0#
bx "
b0 !
$end
#50
b11000000 "
b11000000 ,
b11000000 B
b0 /
0(
b0 1
0)
b0 -
b0 8
b0 9
b0 A
0.
00
07
b10 $
b10 &
#70
1.
10
17
b11 $
b11 &
#100
b1 /
b1 1
1#
#200
0#
#300
b1 <
b10 /
b0 1
1)
1#
#400
0#
#500
b11 /
b1 1
1#
#600
0#
#700
b0 /
1(
b0 1
0)
1#
#800
0#
#900
b1 /
b1 1
1#
#1000
0#
#1070
b110 *
b110 5
b110 6
b1100 4
b100 3
b100 %
b100 '
#1100
b10000000 ?
b100 @
b10 <
b10 /
b0 1
1)
1#
#1200
0#
#1300
b11 /
b1 1
1#
#1400
0#
#1500
b0 /
0(
b0 1
0)
1#
#1600
0#
#1700
b1 /
b1 1
1#
#1800
0#
#1900
b110000000 ?
b110 @
b11 <
b10 /
b0 1
1)
1#
#2000
0#
#2100
b11 /
b1 1
1#
#2200
0#
#2300
b1110000111 !
b1110000111 +
b1110000111 :
b1110000111 >
b10000010 "
b10000010 ,
b10000010 B
b110 -
b110 8
b110 9
b110 A
b0 /
1(
b0 1
0)
1#
#2400
0#
#2500
b1 /
b1 1
1#
#2600
0#
#2700
b1111111111 =
b1110000000 ?
b111 @
b0 <
b10 /
b0 1
1)
1#
#2800
0#
#2900
b11 /
b1 1
1#
#3000
0#
#3100
b0 /
0(
b0 1
0)
1#
#3200
0#
#3300
b1 /
b1 1
1#
#3400
0#
#3500
b0 ?
b0 @
b1 <
b10 /
b0 1
1)
1#
#3600
0#
#3700
b11 /
b1 1
1#
#3800
0#
#3900
b0 /
1(
b0 1
0)
1#
#4000
0#
#4100
b1 /
b1 1
1#
#4200
0#
#4300
b10000000 ?
b100 @
b10 <
b10 /
b0 1
1)
1#
#4400
0#
#4500
b11 /
b1 1
1#
#4600
0#
#4700
b0 /
0(
b0 1
0)
1#
#4800
0#
#4900
b1 /
b1 1
1#
#5000
0#
#5100
b110000000 ?
b110 @
b11 <
b10 /
b0 1
1)
1#
#5200
0#
#5300
b11 /
b1 1
1#
#5400
0#
#5500
b0 /
1(
b0 1
0)
1#
#5600
0#
#5700
b1 /
b1 1
1#
#5800
0#
#5900
b0 =
b1110000000 ?
b111 @
b0 <
b10 /
b0 1
1)
1#
#6000
0#
#6100
b11 /
b1 1
1#
#6200
0#
#6300
b0 /
0(
b0 1
0)
1#
#6400
0#
#6500
b1 /
b1 1
1#
#6600
0#
#6700
b0 ?
b0 @
b1 <
b10 /
b0 1
1)
1#
#6800
0#
#6900
b11 /
b1 1
1#
#7000
0#
#7100
b0 /
1(
b0 1
0)
1#
#7200
0#
#7300
b1 /
b1 1
1#
#7400
0#
#7500
b10000000 ?
b100 @
b10 <
b10 /
b0 1
1)
1#
#7600
0#
#7700
b11 /
b1 1
1#
#7800
0#
#7900
b0 /
0(
b0 1
0)
1#
#8000
0#
#8070
b10 *
b10 5
b10 6
b1010 4
b10 3
b10 %
b10 '
#8100
b1 /
b1 1
1#
#8200
0#
#8300
b110000000 ?
b110 @
b11 <
b10 /
b0 1
1)
1#
#8400
0#
#8500
b11 /
b1 1
1#
#8600
0#
#8700
b110000000 !
b110000000 +
b110000000 :
b110000000 >
b10100100 "
b10100100 ,
b10100100 B
b10 -
b10 8
b10 9
b10 A
b0 /
1(
b0 1
0)
1#
#8800
0#
#8900
b1 /
b1 1
1#
#9000
0#
#9100
b1110000000 !
b1110000000 +
b1110000000 :
b1110000000 >
b1111111111 =
b1110000000 ?
b111 @
b0 <
b10 /
b0 1
1)
1#
#9200
0#
#9300
b11 /
b1 1
1#
#9400
0#
#9500
b0 /
0(
b0 1
0)
1#
#9600
0#
#9700
b1 /
b1 1
1#
#9800
0#
#9900
b0 !
b0 +
b0 :
b0 >
b0 ?
b0 @
b1 <
b10 /
b0 1
1)
1#
#10000
0#
#10100
b11 /
b1 1
1#
#10200
0#
#10300
b0 /
1(
b0 1
0)
1#
#10400
0#
#10500
b1 /
b1 1
1#
#10600
0#
#10700
b10000000 !
b10000000 +
b10000000 :
b10000000 >
b10000000 ?
b100 @
b10 <
b10 /
b0 1
1)
1#
#10800
0#
#10900
b11 /
b1 1
1#
#11000
0#
#11100
b0 /
0(
b0 1
0)
1#
#11200
0#
#11300
b1 /
b1 1
1#
#11400
0#
#11500
b110000000 !
b110000000 +
b110000000 :
b110000000 >
b110000000 ?
b110 @
b11 <
b10 /
b0 1
1)
1#
#11600
0#
#11700
b11 /
b1 1
1#
#11800
0#
#11900
b0 /
1(
b0 1
0)
1#
#12000
0#
#12100
b1 /
b1 1
1#
#12200
0#
#12300
b1110000000 !
b1110000000 +
b1110000000 :
b1110000000 >
b0 =
b1110000000 ?
b111 @
b0 <
b10 /
b0 1
1)
1#
#12400
0#
#12500
b11 /
b1 1
1#
#12600
0#
#12700
b0 /
0(
b0 1
0)
1#
#12800
0#
#12900
b1 /
b1 1
1#
#13000
0#
#13100
b0 !
b0 +
b0 :
b0 >
b0 ?
b0 @
b1 <
b10 /
b0 1
1)
1#
#13200
0#
#13300
b11 /
b1 1
1#
#13400
0#
#13500
b0 /
1(
b0 1
0)
1#
#13600
0#
#13700
b1 /
b1 1
1#
#13800
0#
#13900
b10000000 !
b10000000 +
b10000000 :
b10000000 >
b10000000 ?
b100 @
b10 <
b10 /
b0 1
1)
1#
#14000
0#
#14100
b11 /
b1 1
1#
#14200
0#
#14300
b0 /
0(
b0 1
0)
1#
#14400
0#
#14500
b1 /
b1 1
1#
#14600
0#
#14700
b110000000 !
b110000000 +
b110000000 :
b110000000 >
b110000000 ?
b110 @
b11 <
b10 /
b0 1
1)
1#
#14800
0#
#14900
b11 /
b1 1
1#
#15000
0#
#15070
b11 *
b11 5
b11 6
b10 4
02
b1 $
b1 &
#15100
b110 !
b110 +
b110 :
b110 >
b10110000 "
b10110000 ,
b10110000 B
b11 -
b11 8
b11 9
b11 A
b0 /
1(
b0 1
0)
1#
#15200
0#
#15300
b1 /
b1 1
1#
#15400
0#
#15500
b111 !
b111 +
b111 :
b111 >
b1111111111 =
b1110000000 ?
b111 @
b0 <
b10 /
b0 1
1)
1#
#15600
0#
#15700
b11 /
b1 1
1#
#15800
0#
#15900
b0 /
0(
b0 1
0)
1#
#16000
0#
#16100
b1 /
b1 1
1#
#16200
0#
#16300
b0 !
b0 +
b0 :
b0 >
b0 ?
b0 @
b1 <
b10 /
b0 1
1)
1#
#16400
0#
#16500
b11 /
b1 1
1#
#16600
0#
#16700
b0 /
1(
b0 1
0)
1#
#16800
0#
#16900
b1 /
b1 1
1#
#17000
0#
#17100
b100 !
b100 +
b100 :
b100 >
b10000000 ?
b100 @
b10 <
b10 /
b0 1
1)
1#
#17200
0#
#17300
b11 /
b1 1
1#
#17400
0#
#17500
b0 /
0(
b0 1
0)
1#
#17600
0#
#17700
b1 /
b1 1
1#
#17800
0#
#17900
b110 !
b110 +
b110 :
b110 >
b110000000 ?
b110 @
b11 <
b10 /
b0 1
1)
1#
#18000
0#
#18100
b11 /
b1 1
1#
#18200
0#
#18300
b0 /
1(
b0 1
0)
1#
#18400
0#
#18500
b1 /
b1 1
1#
#18600
0#
#18700
b111 !
b111 +
b111 :
b111 >
b0 =
b1110000000 ?
b111 @
b0 <
b10 /
b0 1
1)
1#
#18800
0#
#18900
b11 /
b1 1
1#
#19000
0#
#19100
b0 /
0(
b0 1
0)
1#
#19200
0#
#19300
b1 /
b1 1
1#
#19400
0#
#19500
b0 !
b0 +
b0 :
b0 >
b0 ?
b0 @
b1 <
b10 /
b0 1
1)
1#
#19600
0#
#19700
b11 /
b1 1
1#
#19800
0#
#19900
b0 /
1(
b0 1
0)
1#
#20000
0#
#20100
b1 /
b1 1
1#
#20200
0#
#20300
b100 !
b100 +
b100 :
b100 >
b10000000 ?
b100 @
b10 <
b10 /
b0 1
1)
1#
#20400
0#
#20500
b11 /
b1 1
1#
#20600
0#
#20700
b0 /
0(
b0 1
0)
1#
#20800
0#
#20900
b1 /
b1 1
1#
#21000
0#
#21100
b110 !
b110 +
b110 :
b110 >
b110000000 ?
b110 @
b11 <
b10 /
b0 1
1)
1#
#21200
0#
#21300
b11 /
b1 1
1#
#21400
0#
#21500
b0 /
1(
b0 1
0)
1#
#21600
0#
#21700
b1 /
b1 1
1#
#21800
0#
#21900
b111 !
b111 +
b111 :
b111 >
b1111111111 =
b1110000000 ?
b111 @
b0 <
b10 /
b0 1
1)
1#
#22000
0#
#22070
b1 *
b1 5
b1 6
b1 4
b1 3
b1 %
b1 '
#22100
b11 /
b1 1
1#
#22200
0#
#22300
b0 /
0(
b0 1
0)
1#
#22400
0#
#22500
b1 /
b1 1
1#
#22600
0#
#22700
b0 !
b0 +
b0 :
b0 >
b0 ?
b0 @
b1 <
b10 /
b0 1
1)
1#
#22800
0#
#22900
b11 /
b1 1
1#
#23000
0#
#23100
b1110000111 !
b1110000111 +
b1110000111 :
b1110000111 >
b11111001 "
b11111001 ,
b11111001 B
b1 -
b1 8
b1 9
b1 A
b0 /
1(
b0 1
0)
1#
#23200
0#
#23300
b1 /
b1 1
1#
#23400
0#
#23500
b10000000 ?
b100 @
b10 <
b10 /
b0 1
1)
1#
#23600
0#
#23700
b11 /
b1 1
1#
#23800
0#
#23900
b0 /
0(
b0 1
0)
1#
#24000
0#
#24100
b1 /
b1 1
1#
#24200
0#
#24300
b110000000 ?
b110 @
b11 <
b10 /
b0 1
1)
1#
#24400
0#
#24500
b11 /
b1 1
1#
#24600
0#
#24700
b0 /
1(
b0 1
0)
1#
#24800
0#
#24900
b1 /
b1 1
1#
#25000
0#
#25100
b0 !
b0 +
b0 :
b0 >
b0 =
b1110000000 ?
b111 @
b0 <
b10 /
b0 1
1)
1#
#25200
0#
#25300
b11 /
b1 1
1#
#25400
0#
#25500
b0 /
0(
b0 1
0)
1#
#25600
0#
#25700
b1 /
b1 1
1#
#25800
0#
#25900
b0 ?
b0 @
b1 <
b10 /
b0 1
1)
1#
#26000
0#
#26100
b11 /
b1 1
1#
#26200
0#
#26300
b0 /
1(
b0 1
0)
1#
#26400
0#
#26500
b1 /
b1 1
1#
#26600
0#
#26700
b10000000 ?
b100 @
b10 <
b10 /
b0 1
1)
1#
#26800
0#
#26900
b11 /
b1 1
1#
#27000
0#
#27100
b0 /
0(
b0 1
0)
1#
#27200
0#
#27300
b1 /
b1 1
1#
#27400
0#
#27500
b110000000 ?
b110 @
b11 <
b10 /
b0 1
1)
1#
#27600
0#
#27700
b11 /
b1 1
1#
#27800
0#
#27900
b0 /
1(
b0 1
0)
1#
#28000
0#
#28100
b1 /
b1 1
1#
#28200
0#
#28300
b1110000111 !
b1110000111 +
b1110000111 :
b1110000111 >
b1111111111 =
b1110000000 ?
b111 @
b0 <
b10 /
b0 1
1)
1#
#28400
0#
#28500
b11 /
b1 1
1#
#28600
0#
#28700
b0 /
0(
b0 1
0)
1#
#28800
0#
#28900
b1 /
b1 1
1#
#29000
0#
#29070
b111 4
b111 3
b111 %
b111 '
#29100
b0 ?
b0 @
b1 <
b10 /
b0 1
1)
1#
#29200
0#
#29300
b11 /
b1 1
1#
#29400
0#
#29500
b0 /
1(
b0 1
0)
1#
#29600
0#
#29700
b1 /
b1 1
1#
#29800
0#
#29900
b10000000 ?
b100 @
b10 <
b10 /
b0 1
1)
1#
#30000
0#
#30100
b11 /
b1 1
1#
#30200
0#
#30300
b0 /
0(
b0 1
0)
1#
#30400
0#
#30500
b1 /
b1 1
1#
#30600
0#
#30700
b110000000 ?
b110 @
b11 <
b10 /
b0 1
1)
1#
#30800
0#
#30900
b11 /
b1 1
1#
#31000
0#
#31100
b0 /
1(
b0 1
0)
1#
#31200
0#
#31300
b1 /
b1 1
1#
#31400
0#
#31500
b0 !
b0 +
b0 :
b0 >
b0 =
b1110000000 ?
b111 @
b0 <
b10 /
b0 1
1)
1#
#31600
0#
#31700
b11 /
b1 1
1#
#31800
0#
#31900
b0 /
0(
b0 1
0)
1#
#32000
0#
#32100
b1 /
b1 1
1#
#32200
0#
#32300
b0 ?
b0 @
b1 <
b10 /
b0 1
1)
1#
#32400
0#
#32500
b11 /
b1 1
1#
#32600
0#
#32700
b0 /
1(
b0 1
0)
1#
#32800
0#
#32900
b1 /
b1 1
1#
#33000
0#
#33100
b10000000 ?
b100 @
b10 <
b10 /
b0 1
1)
1#
#33200
0#
#33300
b11 /
b1 1
1#
#33400
0#
#33500
b0 /
0(
b0 1
0)
1#
#33600
0#
#33700
b1 /
b1 1
1#
#33800
0#
#33900
b110000000 ?
b110 @
b11 <
b10 /
b0 1
1)
1#
#34000
0#
#34100
b11 /
b1 1
1#
#34200
0#
#34300
b0 /
1(
b0 1
0)
1#
#34400
0#
#34500
b1 /
b1 1
1#
#34600
0#
#34700
b1110000111 !
b1110000111 +
b1110000111 :
b1110000111 >
b1111111111 =
b1110000000 ?
b111 @
b0 <
b10 /
b0 1
1)
1#
#34800
0#
#34900
b11 /
b1 1
1#
#35000
0#
#35100
b0 /
0(
b0 1
0)
1#
#35200
0#
#35300
b1 /
b1 1
1#
#35400
0#
#35500
b0 ?
b0 @
b1 <
b10 /
b0 1
1)
1#
#35600
0#
#35700
b11 /
b1 1
1#
#35800
0#
#35900
b0 /
1(
b0 1
0)
1#
#36000
0#
#36070
b100 *
b100 5
b100 6
b110 4
b110 3
b110 %
b110 '
#36100
b1 /
b1 1
1#
#36200
0#
#36300
b10000000 ?
b100 @
b10 <
b10 /
b0 1
1)
1#
#36400
0#
#36500
b11 /
b1 1
1#
#36600
0#
#36700
b0 /
0(
b0 1
0)
1#
#36800
0#
#36900
b1 /
b1 1
1#
#37000
0#
#37100
b110000000 ?
b110 @
b11 <
b10 /
b0 1
1)
1#
#37200
0#
#37300
b11 /
b1 1
1#
#37400
0#
#37500
b1110000110 !
b1110000110 +
b1110000110 :
b1110000110 >
b10011001 "
b10011001 ,
b10011001 B
b100 -
b100 8
b100 9
b100 A
b0 /
1(
b0 1
0)
1#
#37600
0#
#37700
b1 /
b1 1
1#
#37800
0#
#37900
b1110000111 !
b1110000111 +
b1110000111 :
b1110000111 >
b0 =
b1110000000 ?
b111 @
b0 <
b10 /
b0 1
1)
1#
#38000
0#
#38100
b11 /
b1 1
1#
#38200
0#
#38300
b0 /
0(
b0 1
0)
1#
#38400
0#
#38500
b1 /
b1 1
1#
#38600
0#
#38700
b1110000000 !
b1110000000 +
b1110000000 :
b1110000000 >
b0 ?
b0 @
b1 <
b10 /
b0 1
1)
1#
#38800
0#
#38900
b11 /
b1 1
1#
#39000
0#
#39100
b0 /
1(
b0 1
0)
1#
#39200
0#
#39300
b1 /
b1 1
1#
#39400
0#
#39500
b1110000100 !
b1110000100 +
b1110000100 :
b1110000100 >
b10000000 ?
b100 @
b10 <
b10 /
b0 1
1)
1#
#39600
0#
#39700
b11 /
b1 1
1#
#39800
0#
#39900
b0 /
0(
b0 1
0)
1#
#40000
0#
#40100
b1 /
b1 1
1#
#40200
0#
#40300
b1110000110 !
b1110000110 +
b1110000110 :
b1110000110 >
b110000000 ?
b110 @
b11 <
b10 /
b0 1
1)
1#
#40400
0#
#40500
b11 /
b1 1
1#
#40600
0#
#40700
b0 /
1(
b0 1
0)
1#
#40800
0#
#40900
b1 /
b1 1
1#
#41000
0#
#41100
b1110000111 !
b1110000111 +
b1110000111 :
b1110000111 >
b1111111111 =
b1110000000 ?
b111 @
b0 <
b10 /
b0 1
1)
1#
#41200
0#
#41300
b11 /
b1 1
1#
#41400
0#
#41500
b0 /
0(
b0 1
0)
1#
#41600
0#
#41700
b1 /
b1 1
1#
#41800
0#
#41900
b1110000000 !
b1110000000 +
b1110000000 :
b1110000000 >
b0 ?
b0 @
b1 <
b10 /
b0 1
1)
1#
#42000
0#
#42100
b11 /
b1 1
1#
#42200
0#
#42300
b0 /
1(
b0 1
0)
1#
#42400
0#
#42500
b1 /
b1 1
1#
#42600
0#
#42700
b1110000100 !
b1110000100 +
b1110000100 :
b1110000100 >
b10000000 ?
b100 @
b10 <
b10 /
b0 1
1)
1#
#42800
0#
#42900
b11 /
b1 1
1#
#43000
0#
#43070
b101 *
b101 5
b101 6
b1110 4
12
b11 $
b11 &
#43100
b0 /
0(
b0 1
0)
1#
#43200
0#
#43300
b1 /
b1 1
1#
#43400
0#
#43500
b1110000110 !
b1110000110 +
b1110000110 :
b1110000110 >
b110000000 ?
b110 @
b11 <
b10 /
b0 1
1)
1#
#43600
0#
#43700
b11 /
b1 1
1#
#43800
0#
#43900
b110000111 !
b110000111 +
b110000111 :
b110000111 >
b10010010 "
b10010010 ,
b10010010 B
b101 -
b101 8
b101 9
b101 A
b0 /
1(
b0 1
0)
1#
#44000
0#
#44100
b1 /
b1 1
1#
#44200
0#
#44300
b1110000111 !
b1110000111 +
b1110000111 :
b1110000111 >
b0 =
b1110000000 ?
b111 @
b0 <
b10 /
b0 1
1)
1#
#44400
0#
#44500
b11 /
b1 1
1#
#44600
0#
#44700
b0 /
0(
b0 1
0)
1#
#44800
0#
#44900
b1 /
b1 1
1#
#45000
0#
#45100
b111 !
b111 +
b111 :
b111 >
b0 ?
b0 @
b1 <
b10 /
b0 1
1)
1#
#45200
0#
#45300
b11 /
b1 1
1#
#45400
0#
#45500
b0 /
1(
b0 1
0)
1#
#45600
0#
#45700
b1 /
b1 1
1#
#45800
0#
#45900
b10000111 !
b10000111 +
b10000111 :
b10000111 >
b10000000 ?
b100 @
b10 <
b10 /
b0 1
1)
1#
#46000
0#
#46100
b11 /
b1 1
1#
#46200
0#
#46300
b0 /
0(
b0 1
0)
1#
#46400
0#
#46500
b1 /
b1 1
1#
#46600
0#
#46700
b110000111 !
b110000111 +
b110000111 :
b110000111 >
b110000000 ?
b110 @
b11 <
b10 /
b0 1
1)
1#
#46800
0#
#46900
b11 /
b1 1
1#
#47000
0#
#47100
b0 /
1(
b0 1
0)
1#
#47200
0#
#47300
b1 /
b1 1
1#
#47400
0#
#47500
b1110000111 !
b1110000111 +
b1110000111 :
b1110000111 >
b1111111111 =
b1110000000 ?
b111 @
b0 <
b10 /
b0 1
1)
1#
#47600
0#
#47700
b11 /
b1 1
1#
#47800
0#
#47900
b0 /
0(
b0 1
0)
1#
#48000
0#
#48100
b1 /
b1 1
1#
#48200
0#
#48300
b111 !
b111 +
b111 :
b111 >
b0 ?
b0 @
b1 <
b10 /
b0 1
1)
1#
#48400
0#
#48500
b11 /
b1 1
1#
#48600
0#
#48700
b0 /
1(
b0 1
0)
1#
#48800
0#
#48900
b1 /
b1 1
1#
#49000
0#
#49100
b10000111 !
b10000111 +
b10000111 :
b10000111 >
b10000000 ?
b100 @
b10 <
b10 /
b0 1
1)
1#
#49200
0#
#49300
b11 /
b1 1
1#
#49400
0#
#49500
b0 /
0(
b0 1
0)
1#
#49600
0#
#49700
b1 /
b1 1
1#
#49800
0#
#49900
b110000111 !
b110000111 +
b110000111 :
b110000111 >
b110000000 ?
b110 @
b11 <
b10 /
b0 1
1)
1#
